pymsk/__init__.py
pymsk/highres_io.py
pymsk/highres_viz.py
pymsk/scanco_io.py
pymsk/scanco_read_files.py
pymsk/scanco_viz.py
pymsk/write_files.py
pymsk-0.1.3.dist-info/LICENSE
pymsk-0.1.3.dist-info/METADATA
pymsk-0.1.3.dist-info/WHEEL
pymsk-0.1.3.dist-info/top_level.txt
pymsk-0.1.3.dist-info/RECORD
