Metadata-Version: 2.1
Name: pymsk
Version: 0.1.3
Summary: Package for musculoskeletal (MSK) image analysis
Home-page: https://github.com/JCMSK/pyMSK
Author: Serena Bonaretti, more to come
Author-email: serena.bonaretti.research@gmail.com
License: GNU General Public License v3 (GPLv3)
Platform: UNKNOWN
Classifier: Programming Language :: Python :: 3
Classifier: License :: OSI Approved :: GNU General Public License v3 (GPLv3)
Classifier: Operating System :: OS Independent
Requires-Dist: SimpleITK (>=1.2.4)
Requires-Dist: itk (>=5.1.1)
Requires-Dist: matplotlib (>=3.1.3)
Requires-Dist: ipywidgets (>=7.5.1)
